pymail2/__init__.py
pymail2/core.py
pymail2-0.2.3.dist-info/LICENSE
pymail2-0.2.3.dist-info/METADATA
pymail2-0.2.3.dist-info/WHEEL
pymail2-0.2.3.dist-info/top_level.txt
pymail2-0.2.3.dist-info/RECORD
