Metadata-Version: 2.1
Name: pymail2
Version: 0.2.3
Summary: This is most easiest way to send email using smtp
Home-page: https://github.com/oakdatamechanic/pymail
Author: Avinash Negi
Author-email: avinash.negi2194@gmail.com
Classifier: Programming Language :: Python :: 3
Classifier: License :: OSI Approved :: MIT License
Classifier: Operating System :: OS Independent
Requires-Python: >=3.6
License-File: LICENSE
